uwscli/__init__.py
uwscli/cli.py
uwscli/lcd.py
uwscli/led.py
uwscli/logging_utils.py
uwscli/structs.py
uwscli/system_usb.py
uwscli/tinyuz.py
uwscli/tl_effects.py
uwscli/tlcontroller.py
uwscli/usbutil.py
uwscli/wireless.py
uwscli/data/__init__.py
uwscli/data/twinkle.bin
uwscli-0.4.0.dist-info/licenses/LICENSE
uwscli-0.4.0.dist-info/METADATA
uwscli-0.4.0.dist-info/WHEEL
uwscli-0.4.0.dist-info/entry_points.txt
uwscli-0.4.0.dist-info/top_level.txt
uwscli-0.4.0.dist-info/RECORD
