Metadata-Version: 2.4
Name: uwscli
Version: 0.4.0
Summary: Uni-Wireless-Sync: wireless control toolkit for TL fan receivers
Author: Study Hsueh
License: MIT License
Project-URL: Homepage, https://github.com/phstudy/uni-wireless-sync
Project-URL: Issues, https://github.com/phstudy/uni-wireless-sync/issues
Keywords: lian-li,uni-fan,wireless,lcd
Classifier: Development Status :: 3 - Alpha
Classifier: Environment :: Console
Classifier: Intended Audience :: System Administrators
Classifier: License :: OSI Approved :: MIT License
Classifier: Operating System :: MacOS
Classifier: Operating System :: POSIX :: Linux
Classifier: Programming Language :: Python
Classifier: Programming Language :: Python :: 3
Classifier: Programming Language :: Python :: 3.10
Classifier: Programming Language :: Python :: 3.11
Classifier: Programming Language :: Python :: 3.12
Classifier: Topic :: System :: Hardware :: Universal Serial Bus (USB)
Requires-Python: >=3.10
License-File: LICENSE
Requires-Dist: hidapi>=0.14
Requires-Dist: pyusb>=1.2
Requires-Dist: pycryptodomex>=3.17
Provides-Extra: dev
Requires-Dist: pytest>=7.0; extra == "dev"
Requires-Dist: pytest-cov>=4.0; extra == "dev"
Requires-Dist: ruff>=0.5; extra == "dev"
Requires-Dist: black>=24.0; extra == "dev"
Requires-Dist: mypy>=1.8; extra == "dev"
Provides-Extra: images
Requires-Dist: Pillow>=10.0; extra == "images"
Dynamic: license-file
